cli_config_manager/__init__.py
cli_config_manager/manager.py
cli_config_manager-1.0.0.dist-info/AUTHORS.rst
cli_config_manager-1.0.0.dist-info/LICENSE
cli_config_manager-1.0.0.dist-info/METADATA
cli_config_manager-1.0.0.dist-info/WHEEL
cli_config_manager-1.0.0.dist-info/top_level.txt
cli_config_manager-1.0.0.dist-info/RECORD
