Metadata-Version: 2.1
Name: cli-config-manager
Version: 1.0.0
Summary: A simple configuration file manager designed for CLI applications.
Home-page: https://github.com/ryohare/python-cli-config-manager
Author: Ryan O'Hare
Author-email: peyton.ohare@gmail.com
License: BSD-2-Clause
Project-URL: Documentation, https://python-cli-config-manager.readthedocs.io/
Project-URL: Changelog, https://python-cli-config-manager.readthedocs.io/en/latest/changelog.html
Project-URL: Issue Tracker, https://github.com/ryohare/python-cli-config-manager/issues
Platform: UNKNOWN
Classifier: Development Status :: 5 - Production/Stable
Classifier: Intended Audience :: Developers
Classifier: License :: OSI Approved :: BSD License
Classifier: Operating System :: Unix
Classifier: Operating System :: POSIX
Classifier: Operating System :: Microsoft :: Windows
Classifier: Programming Language :: Python
Classifier: Programming Language :: Python :: 2.7
Classifier: Programming Language :: Python :: 3
Classifier: Programming Language :: Python :: 3.5
Classifier: Programming Language :: Python :: 3.6
Classifier: Programming Language :: Python :: 3.7
Classifier: Programming Language :: Python :: 3.8
Classifier: Programming Language :: Python :: 3.9
Classifier: Programming Language :: Python :: Implementation :: CPython
Classifier: Programming Language :: Python :: Implementation :: PyPy
Classifier: Topic :: Utilities
Requires-Python: >=2.7, !=3.0.*, !=3.1.*, !=3.2.*, !=3.3.*, !=3.4.*
